Metadata-Version: 2.1
Name: web3-token-new
Version: 1.1.0
Summary: Web3 Token implementation for python. And it supports web3 v6.0.0+
Home-page: https://github.com/Ergos1/web3-token-python
Author: Alex Dudko, Yergeldi Zhainbek
Author-email: duke@simfik.ru, ergossteam@gmail.com
License: MIT
Keywords: web,web3,web3-token,etherium,crypto,blockchain
Platform: UNKNOWN
Classifier: Development Status :: 4 - Beta
Classifier: Topic :: Software Development :: Build Tools
Classifier: License :: OSI Approved :: MIT License
Classifier: Programming Language :: Python :: 3
Classifier: Programming Language :: Python :: 3.5
Classifier: Programming Language :: Python :: 3.6
Classifier: Programming Language :: Python :: 3.7
Classifier: Programming Language :: Python :: 3.8
Classifier: Programming Language :: Python :: 3.9
Classifier: Programming Language :: Python :: 3.10
